README.md
setup.py
WSGI_MonkeyType.egg-info/PKG-INFO
WSGI_MonkeyType.egg-info/SOURCES.txt
WSGI_MonkeyType.egg-info/dependency_links.txt
WSGI_MonkeyType.egg-info/requires.txt
WSGI_MonkeyType.egg-info/top_level.txt
wsgi_monkeytype/__init__.py
wsgi_monkeytype/flask.py
wsgi_monkeytype/middleware.py
wsgi_monkeytype/mysql_store.py