Metadata-Version: 2.1
Name: WSGI-MonkeyType
Version: 1.0.0
Summary: some monkeytype utils for wsgi application
Home-page: https://github.com/xiachufang/wsgi-monkeytype
Author: xcf
Author-email: xcf@xiachufang.com
License: BSD
Platform: UNKNOWN
Classifier: Environment :: Web Environment
Classifier: Intended Audience :: Developers
Classifier: License :: OSI Approved :: BSD License
Classifier: Operating System :: OS Independent
Classifier: Programming Language :: Python
Classifier: Topic :: Internet :: WWW/HTTP :: Dynamic Content
Classifier: Topic :: Software Development :: Libraries :: Python Modules
Classifier: Programming Language :: Python :: 3
Classifier: Programming Language :: Python :: 3.5
Classifier: Programming Language :: Python :: 3.6
Classifier: Programming Language :: Python :: 3.7
Provides-Extra: mysql
Provides-Extra: flask
